setup.py
legos/__init__.py
legos/nettools.py
legos.nettools.egg-info/PKG-INFO
legos.nettools.egg-info/SOURCES.txt
legos.nettools.egg-info/dependency_links.txt
legos.nettools.egg-info/namespace_packages.txt
legos.nettools.egg-info/requires.txt
legos.nettools.egg-info/top_level.txt
legos/libs/__init__.py
legos/libs/ICMP/__init__.py
legos/libs/ICMP/ip.py
legos/libs/ICMP/messages.py
legos/libs/ICMP/ping.py
legos/tools/Geoloc.py
legos/tools/Ping.py
legos/tools/Tool.py
legos/tools/Whois.py
legos/tools/__init__.py