Metadata-Version: 1.1
Name: legos.nettools
Version: 0.1.0
Summary: Lego providing networking tools
Home-page: https://github.com/Legobot/legos.nettools
Author: Nitrax
Author-email: UNKNOWN
License: MIT
Platform: UNKNOWN
Classifier: License :: OSI Approved :: MIT License
Classifier: Programming Language :: Python :: 3
